pydifftools/__init__.py
pydifftools/check_numbers.py
pydifftools/command_line.py
pydifftools/command_registry.py
pydifftools/comment_functions.py
pydifftools/continuous.py
pydifftools/copy_files.py
pydifftools/diff-doc.js
pydifftools/doc_contents.py
pydifftools/html_comments.py
pydifftools/html_uncomments.py
pydifftools/match_spaces.py
pydifftools/onewordify.py
pydifftools/onewordify_undo.py
pydifftools/outline.py
pydifftools/rearrange_tex.py
pydifftools/searchacro.py
pydifftools/separate_comments.py
pydifftools/split_conflict.py
pydifftools/unseparate_comments.py
pydifftools/wrap_sentences.py
pydifftools/xml2xlsx.vbs
pydifftools/flowchart/__init__.py
pydifftools/flowchart/dot_to_yaml.py
pydifftools/flowchart/graph.py
pydifftools/flowchart/watch_graph.py
pydifftools/notebook/__init__.py
pydifftools/notebook/fast_build.py
pydifftools/notebook/tex_to_qmd.py
pydifftools-0.1.7.dist-info/licenses/LICENSE.md
pydifftools-0.1.7.dist-info/METADATA
pydifftools-0.1.7.dist-info/WHEEL
pydifftools-0.1.7.dist-info/entry_points.txt
pydifftools-0.1.7.dist-info/top_level.txt
pydifftools-0.1.7.dist-info/RECORD
