Metadata-Version: 2.4
Name: pyDiffTools
Version: 0.1.7
Summary: Diff tools
Author: J M Franck
License: Copyright (c) 2015, jmfranck
License-File: LICENSE.md
Requires-Dist: selenium
Requires-Dist: fuzzywuzzy[speedup]
Requires-Dist: PyYAML>=6.0
Requires-Dist: watchdog
Requires-Dist: pydot
Requires-Dist: python-dateutil
Requires-Dist: jinja2
Requires-Dist: nbformat
Requires-Dist: nbconvert
Requires-Dist: pygments
Requires-Dist: ansi2html
Requires-Dist: lxml
Dynamic: license-file
